{"disruption_id":"OPT-eb07aa80","total_strategies":10,"pareto_front":[{"id":"OPT-5","action":"Current Supplier (RAIL)","carbon_impact":160.7,"cost_impact":6501.86,"delay_impact":17.7,"risk_impact":0.72,"green_resilience_score":74.3,"sustainability_violations":["Exceeds Max Delay by 3.6999999999999993 days"],"recommended":true,"is_pareto_optimal":true,"ideal_distance":0.583},{"id":"OPT-6","action":"Alt Supplier SUP-045 (RAIL)","carbon_impact":182.24,"cost_impact":9152.05,"delay_impact":20.7,"risk_impact":0.41,"green_resilience_score":73.6,"sustainability_violations":["Exceeds Max Delay by 6.699999999999999 days"],"recommended":false,"is_pareto_optimal":true,"ideal_distance":0.701},{"id":"OPT-7","action":"Current Supplier (ROAD)","carbon_impact":964.22,"cost_impact":13003.72,"delay_impact":13.5,"risk_impact":0.72,"green_resilience_score":72.3,"sustainability_violations":[],"recommended":false,"is_pareto_optimal":true,"ideal_distance":0.468},{"id":"OPT-8","action":"Alt Supplier SUP-045 (ROAD)","carbon_impact":1093.44,"cost_impact":16304.09,"delay_impact":16.5,"risk_impact":0.41,"green_resilience_score":71.0,"sustainability_violations":["Exceeds Max Delay by 2.5 days"],"recommended":false,"is_pareto_optimal":true,"ideal_distance":0.595},{"id":"OPT-3","action":"Current Supplier (SEA)","carbon_impact":120.53,"cost_impact":2167.29,"delay_impact":26.0,"risk_impact":0.72,"green_resilience_score":69.0,"sustainability_violations":["Exceeds Max Delay by 12.0 days"],"recommended":false,"is_pareto_optimal":true,"ideal_distance":0.888},{"id":"OPT-4","action":"Alt Supplier SUP-045 (SEA)","carbon_impact":136.68,"cost_impact":4384.02,"delay_impact":29.0,"risk_impact":0.41,"green_resilience_score":68.6,"sustainability_violations":["Exceeds Max Delay by 15.0 days"],"recommended":false,"is_pareto_optimal":true,"ideal_distance":1.001},{"id":"OPT-10","action":"Hybrid Route (Orig Air/Sea)","carbon_impact":5082.23,"cost_impact":27091.09,"delay_impact":3.2,"risk_impact":0.72,"green_resilience_score":60.7,"sustainability_violations":["Exceeds Carbon Budget by 3082.23kg"],"recommended":false,"is_pareto_optimal":true,"ideal_distance":0.621},{"id":"OPT-9","action":"Multi-Supplier Hybrid (Sea/Air)","carbon_impact":5755.28,"cost_impact":30691.83,"delay_impact":5.2,"risk_impact":0.56,"green_resilience_score":56.7,"sustainability_violations":["Exceeds Carbon Budget by 3755.28kg"],"recommended":false,"is_pareto_optimal":true,"ideal_distance":0.716},{"id":"OPT-1","action":"Current Supplier (AIR)","carbon_impact":10043.94,"cost_impact":52014.89,"delay_impact":2.2,"risk_impact":0.72,"green_resilience_score":33.6,"sustainability_violations":["Exceeds Carbon Budget by 8043.94kg"],"recommended":false,"is_pareto_optimal":true,"ideal_distance":1.241},{"id":"OPT-2","action":"Alt Supplier SUP-045 (AIR)","carbon_impact":11390.03,"cost_impact":59216.38,"delay_impact":5.2,"risk_impact":0.41,"green_resilience_score":26.4,"sustainability_violations":["Exceeds Carbon Budget by 9390.03kg"],"recommended":false,"is_pareto_optimal":true,"ideal_distance":1.419}],"dominated_strategies":[],"categories":{"lowest_carbon":{"id":"OPT-3","action":"Current Supplier (SEA)","carbon_impact":120.53,"cost_impact":2167.29,"delay_impact":26.0,"risk_impact":0.72,"green_resilience_score":69.0,"sustainability_violations":["Exceeds Max Delay by 12.0 days"],"recommended":false,"is_pareto_optimal":true,"ideal_distance":0.888},"lowest_cost":{"id":"OPT-3","action":"Current Supplier (SEA)","carbon_impact":120.53,"cost_impact":2167.29,"delay_impact":26.0,"risk_impact":0.72,"green_resilience_score":69.0,"sustainability_violations":["Exceeds Max Delay by 12.0 days"],"recommended":false,"is_pareto_optimal":true,"ideal_distance":0.888},"fastest_recovery":{"id":"OPT-1","action":"Current Supplier (AIR)","carbon_impact":10043.94,"cost_impact":52014.89,"delay_impact":2.2,"risk_impact":0.72,"green_resilience_score":33.6,"sustainability_violations":["Exceeds Carbon Budget by 8043.94kg"],"recommended":false,"is_pareto_optimal":true,"ideal_distance":1.241},"lowest_risk":{"id":"OPT-6","action":"Alt Supplier SUP-045 (RAIL)","carbon_impact":182.24,"cost_impact":9152.05,"delay_impact":20.7,"risk_impact":0.41,"green_resilience_score":73.6,"sustainability_violations":["Exceeds Max Delay by 6.699999999999999 days"],"recommended":false,"is_pareto_optimal":true,"ideal_distance":0.701},"best_balanced":{"id":"OPT-7","action":"Current Supplier (ROAD)","carbon_impact":964.22,"cost_impact":13003.72,"delay_impact":13.5,"risk_impact":0.72,"green_resilience_score":72.3,"sustainability_violations":[],"recommended":false,"is_pareto_optimal":true,"ideal_distance":0.468}},"insights":["The lowest-carbon strategy emits 120.53kg but increases delay by 23.8 days vs the fastest option.","The fastest recovery strategy costs $52014.89 and emits 83.3x more CO₂.","The best balanced strategy reduces emissions while keeping delay to 13.5 days."]}